mihkelBayesian/__init__.py
mihkelBayesian/bayesianfunctions.py
mihkelBayesian/functions.py
mihkelBayesian/optimize.py
mihkelBayesian/tests/__init__.py
mihkelBayesian/tests/test_bayesianfunctions.py
mihkelBayesian/tests/test_functions.py
mihkelBayesian-1.0.0.dist-info/LICENSE.txt
mihkelBayesian-1.0.0.dist-info/METADATA
mihkelBayesian-1.0.0.dist-info/WHEEL
mihkelBayesian-1.0.0.dist-info/top_level.txt
mihkelBayesian-1.0.0.dist-info/RECORD
