Metadata-Version: 2.1
Name: mihkelBayesian
Version: 1.0.0
Summary: Machine learning hyperparameter optimiser using the Bayesian model
Home-page: https://github.com/mihkelKR/mihkelBayesian
Author: Mihkel Kaarel Raidal
Author-email: m.k.raidal@gmail.com
License: MIT
Platform: UNKNOWN
Classifier: Programming Language :: Python :: 3
Classifier: License :: OSI Approved :: MIT License
Classifier: Operating System :: OS Independent
Requires-Python: >=3.6
Requires-Dist: numpy (>=1.18.1)
Requires-Dist: matplotlib (>=3.1.3)
Requires-Dist: sklearn (>=0.0)
Requires-Dist: scipy (>=1.4.1)
